[
  {
    "id": "course-01", "order_num": 1, "is_published": true,
    "title": "Petualangan Gigi", "month_label": "Juli 2025",
    "category_label": "Pengenalan Dasar", "thumbnail_color": "#DCFCE7",
    "description": "Mengenal jenis-jenis gigi sulung dan fungsinya dalam proses makan.",
    "total_lessons": 4, "passing_score": 70,
    "objectives": ["Mengidentifikasi jenis-jenis gigi sulung","Menjelaskan fungsi masing-masing jenis gigi sulung","Membedakan bentuk dan letak gigi"],
    "activities": ["Menghitung dan mengamati gigi menggunakan cermin kecil","Tebak-tebakan jenis gigi sulung","Pemberian stiker bintang"],
    "tools": ["Poster edukasi gigi sulung"]
  },
  {
    "id": "course-02", "order_num": 2, "is_published": true,
    "title": "Perkenalan Alat Pembersih Gigi", "month_label": "Agustus 2025",
    "category_label": "Kebersihan Gigi", "thumbnail_color": "#DBEAFE",
    "description": "Mengenal alat pembersih gigi dan fungsinya melalui media gambar dan benda nyata.",
    "total_lessons": 4, "passing_score": 70,
    "objectives": ["Mengenal alat pembersih gigi","Menyebutkan fungsi masing-masing alat"],
    "activities": ["Anak membawa alat pembersih gigi pribadi","Demonstrasi takaran pasta gigi"],
    "tools": ["Berbagai jenis sikat gigi"]
  },
  {
    "id": "course-03", "order_num": 3, "is_published": true,
    "title": "Waktu dan Cara Menyikat Gigi", "month_label": "September 2025",
    "category_label": "Kebersihan Gigi", "thumbnail_color": "#FEF9C3",
    "description": "Mengetahui manfaat, waktu yang tepat, dan teknik menyikat gigi yang benar.",
    "total_lessons": 4, "passing_score": 70,
    "objectives": ["Mengetahui manfaat menyikat gigi","Menyebutkan waktu yang tepat","Teknik menyikat yang benar"],
    "activities": ["Demonstrasi oleh guru","Praktik bersama","Lagu dua menit"],
    "tools": ["Phantom gigi","Sikat gigi"]
  },
  {
    "id": "course-04", "order_num": 4, "is_published": true,
    "title": "Dokter Gigi, Sahabat Gigi", "month_label": "Oktober 2025",
    "category_label": "Kesehatan Gigi", "thumbnail_color": "#FCE7F3",
    "description": "Mengenal profesi dokter gigi dan menumbuhkan sikap positif terhadap pemeriksaan gigi.",
    "total_lessons": 4, "passing_score": 70,
    "objectives": ["Mengenal profesi dokter gigi","Sikap positif terhadap dokter gigi"],
    "activities": ["Bermain peran Dokter Gigi dan Pasien"],
    "tools": ["Mainan alat dokter gigi"]
  },
  {
    "id": "course-05", "order_num": 5, "is_published": true,
    "title": "Perkenalan Gigi Berlubang", "month_label": "November 2025",
    "category_label": "Kesehatan Gigi", "thumbnail_color": "#FEE2E2",
    "description": "Mengenali perbedaan gigi sehat dan berlubang serta pentingnya perawatan.",
    "total_lessons": 4, "passing_score": 70,
    "objectives": ["Mengenali perbedaan gigi sehat dan berlubang","Memahami pentingnya perawatan"],
    "activities": ["Menempel kertas pada gigi berlubang"],
    "tools": ["Poster perbedaan gigi"]
  },
  {
    "id": "course-06", "order_num": 6, "is_published": true,
    "title": "Makanan yang Jadi Musuh Gigi", "month_label": "Desember 2025",
    "category_label": "Gizi & Gigi", "thumbnail_color": "#FFF7ED",
    "description": "Mengenal jenis makanan yang dapat menyebabkan gigi berlubang.",
    "total_lessons": 4, "passing_score": 70,
    "objectives": ["Mengenali makanan kariogenik","Membedakan makanan baik dan buruk"],
    "activities": ["Permainan kotak Sahabat Gigi dan Musuh Gigi"],
    "tools": ["Kartu bergambar makanan"]
  },
  {
    "id": "course-07", "order_num": 7, "is_published": true,
    "title": "Minuman yang Jadi Musuh Gigi", "month_label": "Januari 2026",
    "category_label": "Gizi & Gigi", "thumbnail_color": "#EDE9FE",
    "description": "Mengenal jenis minuman yang baik dan buruk untuk kesehatan gigi.",
    "total_lessons": 4, "passing_score": 70,
    "objectives": ["Membedakan minuman baik dan buruk untuk gigi"],
    "activities": ["Permainan klasifikasi gambar minuman"],
    "tools": ["Gambar gigi sehat dan berlubang","Klip bergambar minuman"]
  },
  {
    "id": "course-08", "order_num": 8, "is_published": true,
    "title": "Akibat Gigi Berlubang", "month_label": "Februari 2026",
    "category_label": "Kesehatan Gigi", "thumbnail_color": "#FEF2F2",
    "description": "Memahami dampak gigi berlubang terhadap kesehatan dan aktivitas sehari-hari.",
    "total_lessons": 4, "passing_score": 70,
    "objectives": ["Menjelaskan dampak gigi berlubang","Sikap peduli kesehatan gigi"],
    "activities": ["Pembacaan cerita melalui flashcard"],
    "tools": ["Flashcard gigi berlubang"]
  },
  {
    "id": "course-09", "order_num": 9, "is_published": true,
    "title": "Peri Gigi", "month_label": "Maret 2026",
    "category_label": "Tumbuh Kembang", "thumbnail_color": "#F0FDF4",
    "description": "Memahami proses tanggalnya gigi sulung dan tumbuhnya gigi tetap.",
    "total_lessons": 4, "passing_score": 70,
    "objectives": ["Mengetahui proses tanggalnya gigi","Menyadari ini hal normal"],
    "activities": ["Membuat Kotak Peri Gigi","Bermain peran Peri Gigi"],
    "tools": ["Mainan cabut gigi"]
  },
  {
    "id": "course-10", "order_num": 10, "is_published": true,
    "title": "Ayo ke Dokter Gigi", "month_label": "April 2026",
    "category_label": "Kesehatan Gigi", "thumbnail_color": "#F0F9FF",
    "description": "Memahami pentingnya memeriksakan gigi secara rutin ke dokter gigi.",
    "total_lessons": 4, "passing_score": 70,
    "objectives": ["Memahami pentingnya periksa gigi rutin","Sikap berani saat ke dokter gigi"],
    "activities": ["Membaca pop up book bersama"],
    "tools": ["Pop up book"]
  },
  {
    "id": "course-11", "order_num": 11, "is_published": true,
    "title": "Gigi Sehat, Tubuh Kuat", "month_label": "Mei 2026",
    "category_label": "Gizi & Gigi", "thumbnail_color": "#ECFDF5",
    "description": "Mengaitkan kesehatan gigi dengan kesehatan tubuh secara keseluruhan.",
    "total_lessons": 4, "passing_score": 70,
    "objectives": ["Mengenal pentingnya kesehatan gigi","Makanan sehat untuk gigi dan tubuh"],
    "activities": ["Sikat Gigi Bersama","Buka Bekal Sehat"],
    "tools": ["Sikat gigi","Phantom gigi"]
  },
  {
    "id": "course-12", "order_num": 12, "is_published": true,
    "title": "Jagalah Gigimu", "month_label": "Juni 2026",
    "category_label": "Review", "thumbnail_color": "#FFF7ED",
    "description": "Mengulas dan memperkuat seluruh materi kesehatan gigi selama setahun.",
    "total_lessons": 4, "passing_score": 70,
    "objectives": ["Mengingat semua materi","Mengetahui pentingnya periksa rutin"],
    "activities": ["Tanya Jawab Interaktif dengan Poster"],
    "tools": ["Poster ringkasan"]
  }
]
